{
  "600":"未登录，请登录之后进行操作",
  "601":"数据签名错误",
  "602":"未登录，请登录之后进行操作",
  "603":"未登录，请登录之后进行操作",
  "604":"未登录，请登录之后进行操作",
  "605":"未登录，请登录之后进行操作",
  "606":"未登录，请登录之后进行操作",
  "607":"未登录，请登录之后进行操作",
  "608":"未登录，请登录之后进行操作",
  "609":"未登录，请登录之后进行操作",
  "610":"未登录，请登录之后进行操作",
  "611":"未登录，请登录之后进行操作",
  "612":"未登录，请登录之后进行操作",
  "613":"未登录，请登录之后进行操作",
  "614":"未登录，请登录之后进行操作",
  "615":"未登录，请登录之后进行操作",
  "616":"未登录，请登录之后进行操作",
  "617":"未登录，请登录之后进行操作",
  "618":"未登录，请登录之后进行操作",
  "619":"未登录，请登录之后进行操作",
  "620":"未登录，请登录之后进行操作",
  "621":"未登录，请登录之后进行操作",
  "622":"未登录，请登录之后进行操作",
  "623":"未登录，请登录之后进行操作",
  "624":"未登录，请登录之后进行操作",
  "625":"未登录，请登录之后进行操作",
  "626":"未登录，请登录之后进行操作",
  "627":"未登录，请登录之后进行操作",
  "628":"未登录，请登录之后进行操作"
}